pycounts_toy_python_524/__init__.py
pycounts_toy_python_524/plotting.py
pycounts_toy_python_524/pycounts_toy_python_524.py
pycounts_toy_python_524-0.1.0.dist-info/LICENSE
pycounts_toy_python_524-0.1.0.dist-info/METADATA
pycounts_toy_python_524-0.1.0.dist-info/WHEEL
pycounts_toy_python_524-0.1.0.dist-info/RECORD
