Metadata-Version: 2.1
Name: pycounts_toy_python_524
Version: 0.1.0
Summary: A package based on the pycounts tutorial, as part of DSCI 524 Individual Assignment
License: MIT
Author: Gretel Tan
Requires-Python: >=3.9
Classifier: License :: OSI Approved :: MIT License
Classifier: Programming Language :: Python :: 3
Classifier: Programming Language :: Python :: 3.9
Classifier: Programming Language :: Python :: 3.10
Classifier: Programming Language :: Python :: 3.11
Classifier: Programming Language :: Python :: 3.12
Requires-Dist: matplotlib (>=3.4.3)
